matplotlip/__init__.py
matplotlip/test_fn.py
matplotlip/test_fn2.py
matplotlip-0.2.dist-info/METADATA
matplotlip-0.2.dist-info/WHEEL
matplotlip-0.2.dist-info/top_level.txt
matplotlip-0.2.dist-info/RECORD
